lang_id_local_ray.py
lang_id_s3_ray.py
lang_id_transform_ray.py
dpk_lang_id_transform_ray-0.2.0.dist-info/METADATA
dpk_lang_id_transform_ray-0.2.0.dist-info/WHEEL
dpk_lang_id_transform_ray-0.2.0.dist-info/top_level.txt
dpk_lang_id_transform_ray-0.2.0.dist-info/RECORD
